box_tools_ai.py
box_tools_docgen.py
box_tools_files.py
box_tools_folders.py
box_tools_generic.py
box_tools_metadata.py
box_tools_search.py
mcp_server_box.py
server_context.py
dungngo_mcp_server_box-0.1.3.dist-info/METADATA
dungngo_mcp_server_box-0.1.3.dist-info/WHEEL
dungngo_mcp_server_box-0.1.3.dist-info/top_level.txt
dungngo_mcp_server_box-0.1.3.dist-info/RECORD
